py_shiftmanager/__init__.py
py_shiftmanager/exceptions.py
py_shiftmanager/logger.py
py_shiftmanager/shiftmanager_compute.py
py_shiftmanager/shiftmanager_io.py
py_shiftmanager/worker.py
py_shiftmanager-0.1.0.dist-info/METADATA
py_shiftmanager-0.1.0.dist-info/WHEEL
py_shiftmanager-0.1.0.dist-info/top_level.txt
py_shiftmanager-0.1.0.dist-info/RECORD
