Metadata-Version: 2.1
Name: py-shiftmanager
Version: 0.1.0
Summary: A simplified, all-in-one shop for handling multithreading/multiprocessing using a managed queue system.
Classifier: Programming Language :: Python :: 3
Classifier: License :: OSI Approved :: MIT License
Classifier: Operating System :: OS Independent
Requires-Dist: dill (==0.3.6)
